[
  {
    "section": "Introdução",
    "order": 1,
    "path": "/docs/1_Introdução",
    "pages": [
      {
        "title": "Bem-vindo à Documentação",
        "path": "/docs/1_Introdução/bem-vindo",
        "order": 1,
        "description": null,
        "tags": null
      },
      {
        "title": "Como Usar o Sistema",
        "path": "/docs/1_Introdução/como-usar",
        "order": 2,
        "description": "Guia básico de utilização da documentação interna",
        "tags": [
          "tutorial",
          "básico",
          "guia"
        ]
      },
      {
        "title": "Guia de Instalação",
        "path": "/docs/1_Introdução/instalacao",
        "order": 2,
        "description": null,
        "tags": null
      }
    ]
  },
  {
    "section": "Guias",
    "order": 3,
    "path": "/docs/3_Guias",
    "pages": [
      {
        "title": "Configuração do Sistema",
        "path": "/docs/3_Guias/configuracao",
        "order": 1,
        "description": "Guia completo de configuração e personalização",
        "tags": [
          "configuração",
          "setup",
          "personalização"
        ]
      },
      {
        "title": "Guia de Deploy",
        "path": "/docs/3_Guias/deploy",
        "order": 2,
        "description": "Como fazer deploy da documentação em diferentes plataformas",
        "tags": [
          "deploy",
          "produção",
          "hosting"
        ]
      }
    ]
  },
  {
    "section": "Tutoriais",
    "order": 4,
    "path": "/docs/4_Tutoriais",
    "pages": [
      {
        "title": "Tutorial Avançado",
        "path": "/docs/4_Tutoriais/avancado",
        "order": 1,
        "description": "Aprenda funcionalidades avançadas do sistema de documentação",
        "tags": [
          "tutorial",
          "avançado",
          "markdown"
        ]
      }
    ]
  }
]